<?xml version="1.0" encoding="UTF-8" standalone="no"?><events><event><id>0a1bd2e2-bbfd-4236-bb52-96660f13d078</id><sourceId>01fe7d3c-0807-4d36-bb54-cb9eea80fb29</sourceId><timestamp>2021-12-11T16:49:53.373+01:00[Europe/Madrid]</timestamp><value>22.0</value><location><lat>39.3757647327836</lat><lon>-2.104212962512168</lon></location></event><event><id>bc261776-99df-48d9-8460-68f4bdb2fc29</id><sourceId>36f6a2d2-2ad6-483c-bb42-43489a05c30a</sourceId><timestamp>2020-11-27T17:35:55.419+01:00[Europe/Madrid]</timestamp><value>28.0</value><location><lat>42.67135576928219</lat><lon>-7.880370747334184</lon></location></event><event><id>20c78400-a1d6-4fe2-9cbc-d3072f710079</id><sourceId>be969a7f-0f52-494e-808d-c247e950baad</sourceId><timestamp>2023-11-14T03:32:25.897+01:00[Europe/Madrid]</timestamp><value>38.0</value><location><lat>39.41240346441344</lat><lon>-3.900107143983492</lon></location></event><event><id>aa24b28a-307d-4a40-9760-e639ab1f8481</id><sourceId>1435de2b-a422-4f51-9011-c45eab011e67</sourceId><timestamp>2024-09-01T02:04:28.069+02:00[Europe/Madrid]</timestamp><value>30.0</value><location><lat>36.11293263047016</lat><lon>1.480935419589322</lon></location></event><event><id>ef0c46bc-3c87-4b33-a93e-c7bce515d641</id><sourceId>3dcce14c-580d-4527-a1f4-8c425ddb6718</sourceId><timestamp>2020-08-30T23:27:35.117+02:00[Europe/Madrid]</timestamp><value>30.0</value><location><lat>41.10912921682128</lat><lon>3.206094573661</lon></location></event><event><id>e2b1c998-c63a-4472-94db-fa1156306363</id><sourceId>38fda742-02df-41f0-acdc-3838173fa46e</sourceId><timestamp>2022-02-24T21:40:47.950+01:00[Europe/Madrid]</timestamp><value>14.0</value><location><lat>38.080607700218806</lat><lon>-2.8280782357839964</lon></location></event><event><id>0c4c32b2-369b-47a4-a8e3-504c418526f9</id><sourceId>7e8a4b20-882b-4cda-9225-956b06da9b52</sourceId><timestamp>2020-08-07T11:52:04.513+02:00[Europe/Madrid]</timestamp><value>83.0</value><location><lat>43.08364284961856</lat><lon>-2.4514593237495985</lon></location></event><event><id>a9ac4d88-ce21-4efd-b9f3-e0af28e5e871</id><sourceId>b88bbc31-7bc1-48d1-a67f-8c125f0e1ef9</sourceId><timestamp>2021-01-26T00:30:40.803+01:00[Europe/Madrid]</timestamp><value>17.0</value><location><lat>40.59235169047967</lat><lon>-7.543271529619965</lon></location></event><event><id>e76d550a-aafe-4483-b5c5-1d071b7dcb88</id><sourceId>3752456d-2428-4c6b-8bdc-fcbae7700270</sourceId><timestamp>2025-03-30T00:45:59.007+01:00[Europe/Madrid]</timestamp><value>80.0</value><location><lat>40.567737213036054</lat><lon>-8.62653423583694</lon></location></event><event><id>8ae5f725-67e7-4ff2-9eef-7edff2efdd0c</id><sourceId>4fa1444b-370f-4920-b52f-e4a4fc26906a</sourceId><timestamp>2021-01-25T00:34:24.542+01:00[Europe/Madrid]</timestamp><value>91.0</value><location><lat>42.23906092142693</lat><lon>-0.7592623667001348</lon></location></event><event><id>7c8e34ed-055e-43d1-a734-b65f70ae48a9</id><sourceId>01fe7d3c-0807-4d36-bb54-cb9eea80fb29</sourceId><timestamp>2023-03-08T17:50:48.363+01:00[Europe/Madrid]</timestamp><value>27.0</value><location><lat>39.58717922677041</lat><lon>1.2772608261079377</lon></location></event><event><id>23dcf07c-4183-479d-b735-4b16fd173ad7</id><sourceId>36f6a2d2-2ad6-483c-bb42-43489a05c30a</sourceId><timestamp>2025-03-18T03:53:25.876+01:00[Europe/Madrid]</timestamp><value>22.0</value><location><lat>40.96528605247762</lat><lon>-5.060403119787534</lon></location></event><event><id>e20256df-410f-46df-8849-293294783e7a</id><sourceId>be969a7f-0f52-494e-808d-c247e950baad</sourceId><timestamp>2025-03-10T04:16:17.631+01:00[Europe/Madrid]</timestamp><value>34.0</value><location><lat>38.378928425536664</lat><lon>-9.152240254120262</lon></location></event><event><id>22718fb7-7a96-4bfb-980f-479c27dde454</id><sourceId>1435de2b-a422-4f51-9011-c45eab011e67</sourceId><timestamp>2024-08-02T07:44:44.213+02:00[Europe/Madrid]</timestamp><value>84.0</value><location><lat>44.174208339540925</lat><lon>-7.21904747071326</lon></location></event><event><id>75d31deb-7216-4dd2-83bc-8f552d203a20</id><sourceId>3dcce14c-580d-4527-a1f4-8c425ddb6718</sourceId><timestamp>2023-10-22T17:25:16.096+02:00[Europe/Madrid]</timestamp><value>75.0</value><location><lat>42.75076761310063</lat><lon>1.561476703906063</lon></location></event><event><id>f6b74aa2-e05c-49a6-953f-959971ac6ecb</id><sourceId>38fda742-02df-41f0-acdc-3838173fa46e</sourceId><timestamp>2023-04-14T10:13:13.958+02:00[Europe/Madrid]</timestamp><value>50.0</value><location><lat>36.424444459147445</lat><lon>1.2791244592090667</lon></location></event><event><id>ef5f0b9f-96e3-44ec-8ec6-3be5a70c60d3</id><sourceId>7e8a4b20-882b-4cda-9225-956b06da9b52</sourceId><timestamp>2024-01-12T06:45:44.977+01:00[Europe/Madrid]</timestamp><value>36.0</value><location><lat>39.71342522468597</lat><lon>2.8645281798678592</lon></location></event><event><id>f226a1aa-61a9-4d7e-877f-948a174947be</id><sourceId>b88bbc31-7bc1-48d1-a67f-8c125f0e1ef9</sourceId><timestamp>2024-11-16T21:11:12.217+01:00[Europe/Madrid]</timestamp><value>99.0</value><location><lat>42.61125666533867</lat><lon>-0.5020406622296996</lon></location></event><event><id>8f5bc966-e41e-4a03-8e67-8d5501bab5bd</id><sourceId>3752456d-2428-4c6b-8bdc-fcbae7700270</sourceId><timestamp>2020-07-17T05:59:57.631+02:00[Europe/Madrid]</timestamp><value>23.0</value><location><lat>42.840268016036696</lat><lon>-5.2600240718802915</lon></location></event><event><id>4fec22f6-1fa8-4311-aefe-ce4cf34b5949</id><sourceId>4fa1444b-370f-4920-b52f-e4a4fc26906a</sourceId><timestamp>2025-03-25T08:54:17.154+01:00[Europe/Madrid]</timestamp><value>95.0</value><location><lat>44.149746343460436</lat><lon>-9.407903505913172</lon></location></event><event><id>a82ca622-d40e-4306-854d-1ffe4b1e841c</id><sourceId>01fe7d3c-0807-4d36-bb54-cb9eea80fb29</sourceId><timestamp>2020-09-08T20:39:43.108+02:00[Europe/Madrid]</timestamp><value>8.0</value><location><lat>44.43464006922378</lat><lon>-5.060676474220049</lon></location></event><event><id>85620f24-6bb0-4c36-b2fa-e63f781f77ca</id><sourceId>36f6a2d2-2ad6-483c-bb42-43489a05c30a</sourceId><timestamp>2025-02-21T12:23:07.561+01:00[Europe/Madrid]</timestamp><value>24.0</value><location><lat>43.30260968996862</lat><lon>-3.008121644608421</lon></location></event><event><id>9788bc97-d60b-4f49-b011-e3bd376a3548</id><sourceId>be969a7f-0f52-494e-808d-c247e950baad</sourceId><timestamp>2021-03-08T07:16:44.518+01:00[Europe/Madrid]</timestamp><value>17.0</value><location><lat>43.209929076684126</lat><lon>-8.069100454016453</lon></location></event><event><id>8a08008c-78a5-4c81-a412-755f8beef1d9</id><sourceId>1435de2b-a422-4f51-9011-c45eab011e67</sourceId><timestamp>2025-03-31T10:40:21.816+02:00[Europe/Madrid]</timestamp><value>17.0</value><location><lat>37.42003263244208</lat><lon>-1.0278575512357353</lon></location></event><event><id>72d95be9-4c3b-4fd2-a014-c45f94a0de93</id><sourceId>3dcce14c-580d-4527-a1f4-8c425ddb6718</sourceId><timestamp>2025-03-06T10:18:37.085+01:00[Europe/Madrid]</timestamp><value>94.0</value><location><lat>37.81243583025055</lat><lon>1.992867298714902</lon></location></event><event><id>f0eeee51-e3cd-4eeb-9aa8-681009bf3419</id><sourceId>38fda742-02df-41f0-acdc-3838173fa46e</sourceId><timestamp>2024-02-27T10:12:22.040+01:00[Europe/Madrid]</timestamp><value>96.0</value><location><lat>40.9843044155401</lat><lon>-2.7798712001893753</lon></location></event><event><id>c3c7c082-9d85-4664-a990-5aa37b7573cf</id><sourceId>7e8a4b20-882b-4cda-9225-956b06da9b52</sourceId><timestamp>2025-03-20T06:58:32.693+01:00[Europe/Madrid]</timestamp><value>98.0</value><location><lat>40.142125153474076</lat><lon>-5.7464121450053165</lon></location></event><event><id>2a86d6ed-2aa6-437b-8b8a-3ceba96f410a</id><sourceId>b88bbc31-7bc1-48d1-a67f-8c125f0e1ef9</sourceId><timestamp>2024-09-25T14:24:33.481+02:00[Europe/Madrid]</timestamp><value>13.0</value><location><lat>40.4767274104089</lat><lon>-8.107264998733424</lon></location></event><event><id>29c54849-08c1-4688-aa1d-b037e040d006</id><sourceId>3752456d-2428-4c6b-8bdc-fcbae7700270</sourceId><timestamp>2021-03-14T18:08:52.288+01:00[Europe/Madrid]</timestamp><value>13.0</value><location><lat>37.051339080401924</lat><lon>-9.142922797916551</lon></location></event><event><id>e420744e-a710-4883-bb6a-67d0b7c65b48</id><sourceId>4fa1444b-370f-4920-b52f-e4a4fc26906a</sourceId><timestamp>2022-01-14T14:40:37.799+01:00[Europe/Madrid]</timestamp><value>83.0</value><location><lat>41.20940035672696</lat><lon>-1.971642489069536</lon></location></event><event><id>7873f987-38e5-479c-af4b-9953a0c3349e</id><sourceId>01fe7d3c-0807-4d36-bb54-cb9eea80fb29</sourceId><timestamp>2021-05-19T03:27:49.352+02:00[Europe/Madrid]</timestamp><value>74.0</value><location><lat>43.62654576936747</lat><lon>-8.693711831793225</lon></location></event><event><id>c35f797f-7beb-4f39-bfd3-2214533b34e2</id><sourceId>36f6a2d2-2ad6-483c-bb42-43489a05c30a</sourceId><timestamp>2025-04-02T19:53:51.499+02:00[Europe/Madrid]</timestamp><value>22.0</value><location><lat>44.38945481144128</lat><lon>-8.94645146500305</lon></location></event><event><id>c883b181-4741-4f1b-a9d3-5312c2007b73</id><sourceId>be969a7f-0f52-494e-808d-c247e950baad</sourceId><timestamp>2023-01-14T00:48:25.868+01:00[Europe/Madrid]</timestamp><value>57.0</value><location><lat>36.383207044843495</lat><lon>-5.5880465617629955</lon></location></event><event><id>79d9c8c6-b956-4852-88bd-32bef30e2bab</id><sourceId>1435de2b-a422-4f51-9011-c45eab011e67</sourceId><timestamp>2024-09-27T16:41:01.120+02:00[Europe/Madrid]</timestamp><value>35.0</value><location><lat>41.308321570074746</lat><lon>3.4997277602756522</lon></location></event><event><id>89cb8c71-1a05-4a10-b705-5f33ce9e3e53</id><sourceId>3dcce14c-580d-4527-a1f4-8c425ddb6718</sourceId><timestamp>2023-04-23T02:19:19.265+02:00[Europe/Madrid]</timestamp><value>64.0</value><location><lat>41.32883925918364</lat><lon>3.1497216064131983</lon></location></event><event><id>19df2019-fef3-4c5b-bc2d-d053bf710a90</id><sourceId>38fda742-02df-41f0-acdc-3838173fa46e</sourceId><timestamp>2023-12-11T08:27:40.496+01:00[Europe/Madrid]</timestamp><value>32.0</value><location><lat>37.17360677132692</lat><lon>3.4201787942822524</lon></location></event><event><id>04989c59-23d4-42f7-8566-9a823f04d0e1</id><sourceId>7e8a4b20-882b-4cda-9225-956b06da9b52</sourceId><timestamp>2024-05-08T23:06:37.055+02:00[Europe/Madrid]</timestamp><value>4.0</value><location><lat>41.974347264136625</lat><lon>-4.3966750990603245</lon></location></event><event><id>b0f205af-3b9d-4573-b222-223f19c6a771</id><sourceId>b88bbc31-7bc1-48d1-a67f-8c125f0e1ef9</sourceId><timestamp>2024-10-17T16:33:58.285+02:00[Europe/Madrid]</timestamp><value>49.0</value><location><lat>42.72615286759997</lat><lon>-1.6274315297260706</lon></location></event><event><id>af10bc81-f4bc-420b-ba60-696728e6c41d</id><sourceId>3752456d-2428-4c6b-8bdc-fcbae7700270</sourceId><timestamp>2020-10-29T14:46:41.157+01:00[Europe/Madrid]</timestamp><value>75.0</value><location><lat>37.498709287124996</lat><lon>-2.9534921891918957</lon></location></event><event><id>694b7e4b-f1f7-4cc2-a7eb-9f08ae32b557</id><sourceId>4fa1444b-370f-4920-b52f-e4a4fc26906a</sourceId><timestamp>2023-12-07T03:31:11.530+01:00[Europe/Madrid]</timestamp><value>18.0</value><location><lat>41.90986638871981</lat><lon>2.2072205861251426</lon></location></event><event><id>6a597b8e-bc31-4f81-958c-5acca94a028f</id><sourceId>01fe7d3c-0807-4d36-bb54-cb9eea80fb29</sourceId><timestamp>2021-05-01T02:58:12.802+02:00[Europe/Madrid]</timestamp><value>69.0</value><location><lat>39.39709053894488</lat><lon>0.09145514910068009</lon></location></event><event><id>eed633b5-a1f7-4a6d-81dd-05a135e489aa</id><sourceId>36f6a2d2-2ad6-483c-bb42-43489a05c30a</sourceId><timestamp>2020-10-03T19:37:25.306+02:00[Europe/Madrid]</timestamp><value>99.0</value><location><lat>39.48688774481409</lat><lon>-8.723619274626996</lon></location></event><event><id>18e0026e-ba52-43a5-b77e-d2b96516eb1f</id><sourceId>be969a7f-0f52-494e-808d-c247e950baad</sourceId><timestamp>2024-04-25T17:04:15.240+02:00[Europe/Madrid]</timestamp><value>63.0</value><location><lat>43.56746391784801</lat><lon>-3.7935493058066916</lon></location></event><event><id>21e51922-c720-4ea6-8301-ae4e3b222318</id><sourceId>1435de2b-a422-4f51-9011-c45eab011e67</sourceId><timestamp>2022-03-23T09:02:40.069+01:00[Europe/Madrid]</timestamp><value>77.0</value><location><lat>39.61568239908967</lat><lon>-6.445294963094833</lon></location></event><event><id>7dc10371-64fb-4816-bc8b-a268c56d9bcb</id><sourceId>3dcce14c-580d-4527-a1f4-8c425ddb6718</sourceId><timestamp>2022-08-24T01:12:18.124+02:00[Europe/Madrid]</timestamp><value>78.0</value><location><lat>42.415816206631916</lat><lon>-6.2194947551351945</lon></location></event><event><id>e7d7e3ce-06c0-4da9-b73e-2b25efe8640e</id><sourceId>38fda742-02df-41f0-acdc-3838173fa46e</sourceId><timestamp>2022-11-21T23:31:40.892+01:00[Europe/Madrid]</timestamp><value>85.0</value><location><lat>38.034630873019196</lat><lon>-1.4637936976141503</lon></location></event><event><id>efad6afc-0497-4cce-88eb-f9ecaefd5b43</id><sourceId>7e8a4b20-882b-4cda-9225-956b06da9b52</sourceId><timestamp>2024-09-11T19:42:47.851+02:00[Europe/Madrid]</timestamp><value>13.0</value><location><lat>41.685017937709674</lat><lon>-4.212317887336943</lon></location></event><event><id>bd0ef9a7-9682-4e07-b81e-e74de8caad80</id><sourceId>b88bbc31-7bc1-48d1-a67f-8c125f0e1ef9</sourceId><timestamp>2022-07-25T03:55:24.280+02:00[Europe/Madrid]</timestamp><value>2.0</value><location><lat>36.11869735798874</lat><lon>0.14789610228031336</lon></location></event><event><id>19e5b276-c871-49c3-ba21-f6c1f29b7cf1</id><sourceId>3752456d-2428-4c6b-8bdc-fcbae7700270</sourceId><timestamp>2023-10-30T14:14:58.277+01:00[Europe/Madrid]</timestamp><value>78.0</value><location><lat>40.337432726257845</lat><lon>-5.5211396037232365</lon></location></event><event><id>474d7842-9f45-41bb-9ad9-c7b25c8f1ef5</id><sourceId>4fa1444b-370f-4920-b52f-e4a4fc26906a</sourceId><timestamp>2022-08-11T07:38:28.576+02:00[Europe/Madrid]</timestamp><value>45.0</value><location><lat>36.20175243268817</lat><lon>2.295352285677085</lon></location></event><event><id>589a81f7-5d23-4a79-bef5-7bfa2e85e660</id><sourceId>01fe7d3c-0807-4d36-bb54-cb9eea80fb29</sourceId><timestamp>2021-07-07T23:39:26.146+02:00[Europe/Madrid]</timestamp><value>99.0</value><location><lat>44.446349376138656</lat><lon>3.403666575834615</lon></location></event><event><id>f646e6a4-cb5d-400c-8d42-e67645bd7130</id><sourceId>36f6a2d2-2ad6-483c-bb42-43489a05c30a</sourceId><timestamp>2020-10-14T07:14:03.627+02:00[Europe/Madrid]</timestamp><value>44.0</value><location><lat>39.182129976945944</lat><lon>-4.46955236213406</lon></location></event><event><id>01ea017b-f58b-4a8c-abad-ef9200b8beaa</id><sourceId>be969a7f-0f52-494e-808d-c247e950baad</sourceId><timestamp>2023-06-20T23:46:50.339+02:00[Europe/Madrid]</timestamp><value>57.0</value><location><lat>43.676308695569105</lat><lon>1.9403110503155148</lon></location></event><event><id>4079da5f-f536-4b82-8248-54d36ee2f9dd</id><sourceId>1435de2b-a422-4f51-9011-c45eab011e67</sourceId><timestamp>2023-02-09T04:14:09.181+01:00[Europe/Madrid]</timestamp><value>83.0</value><location><lat>42.0539963778173</lat><lon>-2.293521694925124</lon></location></event><event><id>89579b3e-d152-4006-b3d1-8a776b4c40b3</id><sourceId>3dcce14c-580d-4527-a1f4-8c425ddb6718</sourceId><timestamp>2021-08-19T09:22:16.903+02:00[Europe/Madrid]</timestamp><value>82.0</value><location><lat>42.55740763060368</lat><lon>-5.113936725940278</lon></location></event><event><id>d6d57689-e387-4af4-968f-0f5718089470</id><sourceId>38fda742-02df-41f0-acdc-3838173fa46e</sourceId><timestamp>2025-02-21T06:25:04.882+01:00[Europe/Madrid]</timestamp><value>23.0</value><location><lat>43.63210863548114</lat><lon>-1.6390822885425838</lon></location></event><event><id>43d8ca5b-66eb-4b3d-83cd-be8e9455270a</id><sourceId>7e8a4b20-882b-4cda-9225-956b06da9b52</sourceId><timestamp>2023-10-04T00:14:33.675+02:00[Europe/Madrid]</timestamp><value>26.0</value><location><lat>36.883658163107775</lat><lon>1.53609758933678</lon></location></event><event><id>dd520159-a030-4a98-aeb2-88c974391fdc</id><sourceId>b88bbc31-7bc1-48d1-a67f-8c125f0e1ef9</sourceId><timestamp>2023-10-01T18:37:47.094+02:00[Europe/Madrid]</timestamp><value>68.0</value><location><lat>43.36254155464233</lat><lon>0.9410410656179931</lon></location></event><event><id>58888193-1939-4c28-8a7a-5d09bafaf665</id><sourceId>3752456d-2428-4c6b-8bdc-fcbae7700270</sourceId><timestamp>2021-01-10T14:49:31.821+01:00[Europe/Madrid]</timestamp><value>76.0</value><location><lat>40.19047566504661</lat><lon>-5.446550051155424</lon></location></event><event><id>bbbd0aa3-66e0-4d0a-a0d7-82e469094106</id><sourceId>4fa1444b-370f-4920-b52f-e4a4fc26906a</sourceId><timestamp>2024-02-13T09:21:51.950+01:00[Europe/Madrid]</timestamp><value>21.0</value><location><lat>37.236960059025485</lat><lon>-4.13735551814151</lon></location></event><event><id>626072b5-184c-4522-be93-9245a10275b1</id><sourceId>01fe7d3c-0807-4d36-bb54-cb9eea80fb29</sourceId><timestamp>2022-11-29T03:17:14.497+01:00[Europe/Madrid]</timestamp><value>87.0</value><location><lat>37.89138042543025</lat><lon>1.3078118918736443</lon></location></event><event><id>fb1d1b05-7f8e-4a12-8f3f-5cc87eb92fd5</id><sourceId>36f6a2d2-2ad6-483c-bb42-43489a05c30a</sourceId><timestamp>2020-09-06T18:13:12.782+02:00[Europe/Madrid]</timestamp><value>43.0</value><location><lat>42.45301637134725</lat><lon>-2.2329001092970193</lon></location></event><event><id>88f252f4-77da-4600-a75a-92367e91f5b4</id><sourceId>be969a7f-0f52-494e-808d-c247e950baad</sourceId><timestamp>2022-03-15T01:22:25.238+01:00[Europe/Madrid]</timestamp><value>42.0</value><location><lat>37.77898495185171</lat><lon>3.2359036779193033</lon></location></event><event><id>991380ea-0650-4850-9ddf-e23a383aa116</id><sourceId>1435de2b-a422-4f51-9011-c45eab011e67</sourceId><timestamp>2024-03-16T16:24:05.452+01:00[Europe/Madrid]</timestamp><value>22.0</value><location><lat>40.088449299621935</lat><lon>0.21697911808771408</lon></location></event><event><id>f7901923-b914-420e-bfb1-a9c122934b6f</id><sourceId>3dcce14c-580d-4527-a1f4-8c425ddb6718</sourceId><timestamp>2021-12-10T02:06:39.918+01:00[Europe/Madrid]</timestamp><value>70.0</value><location><lat>39.22035006632953</lat><lon>1.1511574677034488</lon></location></event><event><id>d242b1f8-614d-407c-a2af-1c6f39738d67</id><sourceId>38fda742-02df-41f0-acdc-3838173fa46e</sourceId><timestamp>2021-03-03T09:25:33.268+01:00[Europe/Madrid]</timestamp><value>2.0</value><location><lat>41.68146505553794</lat><lon>1.4454785512380877</lon></location></event><event><id>5eda6d3d-b21f-4a6e-9fc3-dbe2b421f65a</id><sourceId>7e8a4b20-882b-4cda-9225-956b06da9b52</sourceId><timestamp>2024-09-05T10:33:06.544+02:00[Europe/Madrid]</timestamp><value>74.0</value><location><lat>43.00178347400057</lat><lon>-3.1945570999810347</lon></location></event><event><id>a52dc538-dbb4-4af2-a98a-543f3d23e9f2</id><sourceId>b88bbc31-7bc1-48d1-a67f-8c125f0e1ef9</sourceId><timestamp>2025-03-10T10:11:17.926+01:00[Europe/Madrid]</timestamp><value>41.0</value><location><lat>37.234974755871896</lat><lon>1.6498810898532952</lon></location></event><event><id>5f313987-aa89-448b-a4e2-11d71f24bd33</id><sourceId>3752456d-2428-4c6b-8bdc-fcbae7700270</sourceId><timestamp>2023-04-10T10:42:00.259+02:00[Europe/Madrid]</timestamp><value>66.0</value><location><lat>38.903163001085304</lat><lon>-4.61942630076288</lon></location></event><event><id>0b2b3749-cc37-476a-a20f-88ae11ac71c6</id><sourceId>4fa1444b-370f-4920-b52f-e4a4fc26906a</sourceId><timestamp>2024-03-03T10:32:14.091+01:00[Europe/Madrid]</timestamp><value>85.0</value><location><lat>43.287269869246046</lat><lon>-2.8057090754832164</lon></location></event><event><id>1d8f283d-2a17-49a0-9b0c-a0db2a5043aa</id><sourceId>01fe7d3c-0807-4d36-bb54-cb9eea80fb29</sourceId><timestamp>2021-02-20T12:46:36.754+01:00[Europe/Madrid]</timestamp><value>96.0</value><location><lat>37.706857990681634</lat><lon>1.9623273601424067</lon></location></event><event><id>5a962f1d-160e-4e9c-aabc-0bcd68a23e34</id><sourceId>36f6a2d2-2ad6-483c-bb42-43489a05c30a</sourceId><timestamp>2025-05-20T10:31:21.080+02:00[Europe/Madrid]</timestamp><value>93.0</value><location><lat>38.316713862362676</lat><lon>0.4618706995716675</lon></location></event><event><id>41f8a117-f392-4aa4-96ff-1d1f666c887a</id><sourceId>be969a7f-0f52-494e-808d-c247e950baad</sourceId><timestamp>2023-09-24T04:59:24.275+02:00[Europe/Madrid]</timestamp><value>17.0</value><location><lat>37.971333396016995</lat><lon>1.924712823370161</lon></location></event><event><id>0632a0f9-c6f9-499d-a8a3-0f7b46cbadc7</id><sourceId>1435de2b-a422-4f51-9011-c45eab011e67</sourceId><timestamp>2024-08-24T12:28:12.784+02:00[Europe/Madrid]</timestamp><value>35.0</value><location><lat>42.37302339177921</lat><lon>-4.0281772620676275</lon></location></event><event><id>c7b7ac72-284f-4a1b-a791-f56bad261bc8</id><sourceId>3dcce14c-580d-4527-a1f4-8c425ddb6718</sourceId><timestamp>2021-08-10T18:57:11.589+02:00[Europe/Madrid]</timestamp><value>48.0</value><location><lat>41.02450708320785</lat><lon>-0.4727811078087054</lon></location></event><event><id>d9bd6d2e-a78a-4e7f-855b-b970b1f57e45</id><sourceId>38fda742-02df-41f0-acdc-3838173fa46e</sourceId><timestamp>2024-05-16T14:02:33.420+02:00[Europe/Madrid]</timestamp><value>55.0</value><location><lat>38.952724578300334</lat><lon>3.251340364672343</lon></location></event><event><id>2bec2d61-7865-4eee-8e18-8c822b6614c3</id><sourceId>7e8a4b20-882b-4cda-9225-956b06da9b52</sourceId><timestamp>2024-05-12T18:55:15.652+02:00[Europe/Madrid]</timestamp><value>3.0</value><location><lat>42.75694532646592</lat><lon>3.4027816231531265</lon></location></event><event><id>099ce38f-b194-4664-a721-974acb069bde</id><sourceId>b88bbc31-7bc1-48d1-a67f-8c125f0e1ef9</sourceId><timestamp>2024-02-01T17:25:50.879+01:00[Europe/Madrid]</timestamp><value>76.0</value><location><lat>42.76135574682268</lat><lon>1.827772515601625</lon></location></event><event><id>7654d98e-efd7-4410-8a71-b431feb8de09</id><sourceId>3752456d-2428-4c6b-8bdc-fcbae7700270</sourceId><timestamp>2023-04-23T23:59:12.202+02:00[Europe/Madrid]</timestamp><value>2.0</value><location><lat>43.419969604327605</lat><lon>-0.5107998779129872</lon></location></event><event><id>46cfc889-a1c4-4248-bb01-45197d8e75ad</id><sourceId>4fa1444b-370f-4920-b52f-e4a4fc26906a</sourceId><timestamp>2020-09-20T12:50:51.676+02:00[Europe/Madrid]</timestamp><value>70.0</value><location><lat>41.12999855890228</lat><lon>-9.918772634074335</lon></location></event><event><id>b3dfc9b0-3e90-4d04-9809-6797fbe12009</id><sourceId>01fe7d3c-0807-4d36-bb54-cb9eea80fb29</sourceId><timestamp>2024-08-25T09:24:20.077+02:00[Europe/Madrid]</timestamp><value>93.0</value><location><lat>42.25875645001919</lat><lon>-4.168260317928395</lon></location></event><event><id>80bd204e-a5a5-415f-ba5a-f677d104cf8a</id><sourceId>36f6a2d2-2ad6-483c-bb42-43489a05c30a</sourceId><timestamp>2024-10-08T07:28:33.941+02:00[Europe/Madrid]</timestamp><value>52.0</value><location><lat>40.47871468390433</lat><lon>-5.927144550537505</lon></location></event><event><id>cbd420b2-bcea-4d37-8cf4-6d22b76f0ffa</id><sourceId>be969a7f-0f52-494e-808d-c247e950baad</sourceId><timestamp>2023-08-02T11:12:05.979+02:00[Europe/Madrid]</timestamp><value>46.0</value><location><lat>36.93550530110243</lat><lon>-2.440345991732281</lon></location></event><event><id>1fde54e0-4f34-480b-a766-81fae923b4bd</id><sourceId>1435de2b-a422-4f51-9011-c45eab011e67</sourceId><timestamp>2022-02-24T11:00:52.003+01:00[Europe/Madrid]</timestamp><value>37.0</value><location><lat>43.344466579518894</lat><lon>-5.660955056274509</lon></location></event><event><id>3c173b16-cb84-4b0f-bf6c-01c5de4bc57e</id><sourceId>3dcce14c-580d-4527-a1f4-8c425ddb6718</sourceId><timestamp>2023-07-13T20:12:06.462+02:00[Europe/Madrid]</timestamp><value>89.0</value><location><lat>41.322755658203576</lat><lon>3.2143593306605247</lon></location></event><event><id>716a3f90-8c7c-4bdf-b73c-df844ebcc303</id><sourceId>38fda742-02df-41f0-acdc-3838173fa46e</sourceId><timestamp>2025-04-08T11:59:45.364+02:00[Europe/Madrid]</timestamp><value>87.0</value><location><lat>38.616098577553146</lat><lon>-1.4832379523640036</lon></location></event><event><id>d6d73713-8181-4c68-9b64-39e3e1a0dc70</id><sourceId>7e8a4b20-882b-4cda-9225-956b06da9b52</sourceId><timestamp>2023-06-06T12:40:13.774+02:00[Europe/Madrid]</timestamp><value>9.0</value><location><lat>43.871928434640495</lat><lon>-4.5179988985023884</lon></location></event><event><id>8752aeff-2c18-4547-9381-6681f64cd9b5</id><sourceId>b88bbc31-7bc1-48d1-a67f-8c125f0e1ef9</sourceId><timestamp>2020-09-26T01:01:29.133+02:00[Europe/Madrid]</timestamp><value>45.0</value><location><lat>38.743959442311</lat><lon>-8.459727352427656</lon></location></event><event><id>484d1658-7b9f-4733-b655-d86593319ca5</id><sourceId>3752456d-2428-4c6b-8bdc-fcbae7700270</sourceId><timestamp>2024-10-25T02:41:21.155+02:00[Europe/Madrid]</timestamp><value>32.0</value><location><lat>43.38717312340067</lat><lon>-2.7418592524317393</lon></location></event><event><id>a8d4f40c-4ff3-4dc4-913d-d85f5922edd1</id><sourceId>4fa1444b-370f-4920-b52f-e4a4fc26906a</sourceId><timestamp>2024-08-31T23:05:16.458+02:00[Europe/Madrid]</timestamp><value>6.0</value><location><lat>38.31674215416132</lat><lon>-1.975520896234885</lon></location></event><event><id>a7a2c287-ae8f-4672-810b-c71a8b86574d</id><sourceId>01fe7d3c-0807-4d36-bb54-cb9eea80fb29</sourceId><timestamp>2024-02-18T18:26:26.065+01:00[Europe/Madrid]</timestamp><value>56.0</value><location><lat>37.659594966655334</lat><lon>-2.6527015532809592</lon></location></event><event><id>83179179-d6e3-40f6-a290-70f8d61a7659</id><sourceId>36f6a2d2-2ad6-483c-bb42-43489a05c30a</sourceId><timestamp>2025-07-15T05:06:02.898+02:00[Europe/Madrid]</timestamp><value>1.0</value><location><lat>42.52311999571756</lat><lon>-4.674894161825802</lon></location></event><event><id>d15b187e-5564-4e2a-854f-37979dda8b2c</id><sourceId>be969a7f-0f52-494e-808d-c247e950baad</sourceId><timestamp>2024-06-11T02:33:22.151+02:00[Europe/Madrid]</timestamp><value>5.0</value><location><lat>38.0419439442524</lat><lon>-1.024908430725496</lon></location></event><event><id>531306fb-8576-4ce3-90bd-b4cf9fc60054</id><sourceId>1435de2b-a422-4f51-9011-c45eab011e67</sourceId><timestamp>2023-01-07T16:50:39.745+01:00[Europe/Madrid]</timestamp><value>76.0</value><location><lat>44.140756529798296</lat><lon>-0.35903073423424914</lon></location></event><event><id>91623505-919d-4c55-9820-90369200127e</id><sourceId>3dcce14c-580d-4527-a1f4-8c425ddb6718</sourceId><timestamp>2024-07-14T10:40:32.610+02:00[Europe/Madrid]</timestamp><value>16.0</value><location><lat>40.66884185626136</lat><lon>2.165694796057103</lon></location></event><event><id>aa1c464f-45df-4916-a2ce-f5ae7877c2ff</id><sourceId>38fda742-02df-41f0-acdc-3838173fa46e</sourceId><timestamp>2025-03-31T13:26:34.505+02:00[Europe/Madrid]</timestamp><value>96.0</value><location><lat>42.32026898990087</lat><lon>2.8985658509074614</lon></location></event><event><id>f3cab927-5fd7-4fb6-b0bd-4d435acc0d33</id><sourceId>7e8a4b20-882b-4cda-9225-956b06da9b52</sourceId><timestamp>2022-02-02T03:23:19.234+01:00[Europe/Madrid]</timestamp><value>93.0</value><location><lat>40.152624692927404</lat><lon>-9.087637138747985</lon></location></event><event><id>fb718b22-6446-4d1e-9aa8-744cda3b5b7b</id><sourceId>b88bbc31-7bc1-48d1-a67f-8c125f0e1ef9</sourceId><timestamp>2025-07-11T01:32:54.938+02:00[Europe/Madrid]</timestamp><value>11.0</value><location><lat>37.05672070912976</lat><lon>-4.965789287267764</lon></location></event><event><id>7ce3fd48-2b17-4858-8f27-0fb2e00ab390</id><sourceId>3752456d-2428-4c6b-8bdc-fcbae7700270</sourceId><timestamp>2021-05-14T18:41:50.408+02:00[Europe/Madrid]</timestamp><value>83.0</value><location><lat>37.709881316853185</lat><lon>-0.5562521338015536</lon></location></event><event><id>27bf2c59-deb4-4b11-829c-46a9b46cb31b</id><sourceId>4fa1444b-370f-4920-b52f-e4a4fc26906a</sourceId><timestamp>2023-04-18T12:22:39.584+02:00[Europe/Madrid]</timestamp><value>59.0</value><location><lat>37.36622394488004</lat><lon>-0.8360326997611622</lon></location></event></events>